{
    "droid_0955": {
        "id": 955,
        "position": [
            5173,
            1721,
            334
        ],
        "rotation": [
            0,
            0,
            0
        ],
        "startpos": 0,
        "template": "ConstructorDroid"
    },
    "droid_0956": {
        "id": 956,
        "position": [
            6470,
            1723,
            334
        ],
        "rotation": [
            0,
            0,
            0
        ],
        "startpos": 0,
        "template": "ConstructorDroid"
    },
    "droid_0957": {
        "id": 957,
        "position": [
            2708,
            6057,
            415
        ],
        "rotation": [
            0,
            0,
            0
        ],
        "startpos": 2,
        "template": "ConstructorDroid"
    },
    "droid_0958": {
        "id": 958,
        "position": [
            1219,
            5569,
            414
        ],
        "rotation": [
            0,
            0,
            0
        ],
        "startpos": 2,
        "template": "ConstructorDroid"
    },
    "droid_0959": {
        "id": 959,
        "position": [
            8779,
            12357,
            450
        ],
        "rotation": [
            0,
            0,
            0
        ],
        "startpos": 1,
        "template": "ConstructorDroid"
    },
    "droid_0960": {
        "id": 960,
        "position": [
            9408,
            13248,
            421
        ],
        "rotation": [
            0,
            0,
            0
        ],
        "startpos": 1,
        "template": "ConstructorDroid"
    },
    "droid_0963": {
        "id": 963,
        "position": [
            13120,
            7872,
            414
        ],
        "rotation": [
            0,
            0,
            0
        ],
        "startpos": 3,
        "template": "ConstructorDroid"
    },
    "droid_0964": {
        "id": 964,
        "position": [
            12992,
            6976,
            414
        ],
        "rotation": [
            0,
            0,
            0
        ],
        "startpos": 3,
        "template": "ConstructorDroid"
    },
    "droid_1115": {
        "id": 1115,
        "player": "scavenger",
        "position": [
            7232,
            8256,
            415
        ],
        "rotation": [
            0,
            0,
            0
        ],
        "template": "BarbarianBuggy"
    },
    "droid_1116": {
        "id": 1116,
        "player": "scavenger",
        "position": [
            7872,
            8768,
            414
        ],
        "rotation": [
            0,
            0,
            0
        ],
        "template": "BarbarianTrike"
    },
    "droid_1117": {
        "id": 1117,
        "player": "scavenger",
        "position": [
            7360,
            9024,
            391
        ],
        "rotation": [
            0,
            0,
            0
        ],
        "template": "BarbarianTrike"
    },
    "droid_1118": {
        "id": 1118,
        "player": "scavenger",
        "position": [
            7104,
            9024,
            378
        ],
        "rotation": [
            0,
            0,
            0
        ],
        "template": "BarbarianTrike"
    },
    "droid_1119": {
        "id": 1119,
        "player": "scavenger",
        "position": [
            7232,
            9024,
            385
        ],
        "rotation": [
            0,
            0,
            0
        ],
        "template": "BarbarianTrike"
    },
    "droid_1120": {
        "id": 1120,
        "player": "scavenger",
        "position": [
            7616,
            9024,
            418
        ],
        "rotation": [
            0,
            0,
            0
        ],
        "template": "BabaJeep"
    },
    "droid_1121": {
        "id": 1121,
        "player": "scavenger",
        "position": [
            7744,
            9024,
            416
        ],
        "rotation": [
            0,
            0,
            0
        ],
        "template": "BabaJeep"
    },
    "droid_1122": {
        "id": 1122,
        "player": "scavenger",
        "position": [
            7616,
            8640,
            415
        ],
        "rotation": [
            0,
            0,
            0
        ],
        "template": "BaBaPeople"
    },
    "droid_1123": {
        "id": 1123,
        "player": "scavenger",
        "position": [
            7744,
            8640,
            415
        ],
        "rotation": [
            0,
            0,
            0
        ],
        "template": "BaBaPeople"
    },
    "droid_1124": {
        "id": 1124,
        "player": "scavenger",
        "position": [
            7616,
            8768,
            415
        ],
        "rotation": [
            0,
            0,
            0
        ],
        "template": "BaBaPeople"
    },
    "droid_1125": {
        "id": 1125,
        "player": "scavenger",
        "position": [
            7744,
            8768,
            414
        ],
        "rotation": [
            0,
            0,
            0
        ],
        "template": "BaBaPeople"
    },
    "droid_1126": {
        "id": 1126,
        "player": "scavenger",
        "position": [
            7104,
            8256,
            415
        ],
        "rotation": [
            50608,
            0,
            0
        ],
        "template": "BabaBusCan"
    },
    "droid_1127": {
        "id": 1127,
        "player": "scavenger",
        "position": [
            7616,
            9280,
            404
        ],
        "rotation": [
            0,
            0,
            0
        ],
        "template": "BabaFireCan"
    }
}
